How2jDisanfangKaifaJiaochengShijianXiangmuMianshitiFix1/README.md
How2jDisanfangKaifaJiaochengShijianXiangmuMianshitiFix1/__init__.py
How2jDisanfangKaifaJiaochengShijianXiangmuMianshitiFix1/__main__.py
How2jDisanfangKaifaJiaochengShijianXiangmuMianshitiFix1/file.epub
How2jDisanfangKaifaJiaochengShijianXiangmuMianshitiFix1/index.html
How2jDisanfangKaifaJiaochengShijianXiangmuMianshitiFix1/css/__init__.py
How2jDisanfangKaifaJiaochengShijianXiangmuMianshitiFix1/css/annotations.css
How2jDisanfangKaifaJiaochengShijianXiangmuMianshitiFix1/css/main.css
How2jDisanfangKaifaJiaochengShijianXiangmuMianshitiFix1/css/normalize.css
How2jDisanfangKaifaJiaochengShijianXiangmuMianshitiFix1/css/popup.css
How2jDisanfangKaifaJiaochengShijianXiangmuMianshitiFix1/font/__init__.py
How2jDisanfangKaifaJiaochengShijianXiangmuMianshitiFix1/font/fontello.eot
How2jDisanfangKaifaJiaochengShijianXiangmuMianshitiFix1/font/fontello.svg
How2jDisanfangKaifaJiaochengShijianXiangmuMianshitiFix1/font/fontello.ttf
How2jDisanfangKaifaJiaochengShijianXiangmuMianshitiFix1/font/fontello.woff
How2jDisanfangKaifaJiaochengShijianXiangmuMianshitiFix1/img/__init__.py
How2jDisanfangKaifaJiaochengShijianXiangmuMianshitiFix1/img/annotator-glyph-sprite.png
How2jDisanfangKaifaJiaochengShijianXiangmuMianshitiFix1/img/annotator-icon-sprite.png
How2jDisanfangKaifaJiaochengShijianXiangmuMianshitiFix1/img/apple-touch-icon.png
How2jDisanfangKaifaJiaochengShijianXiangmuMianshitiFix1/img/cancelfullscreen.png
How2jDisanfangKaifaJiaochengShijianXiangmuMianshitiFix1/img/close.png
How2jDisanfangKaifaJiaochengShijianXiangmuMianshitiFix1/img/fullscreen.png
How2jDisanfangKaifaJiaochengShijianXiangmuMianshitiFix1/img/loader.gif
How2jDisanfangKaifaJiaochengShijianXiangmuMianshitiFix1/img/menu-icon.png
How2jDisanfangKaifaJiaochengShijianXiangmuMianshitiFix1/img/save.png
How2jDisanfangKaifaJiaochengShijianXiangmuMianshitiFix1/img/saved.png
How2jDisanfangKaifaJiaochengShijianXiangmuMianshitiFix1/img/settings-s.png
how2j_disanfang_kaifa_jiaocheng_shijian_xiangmu_mianshiti_fix1-2025.3.25.0.dist-info/METADATA
how2j_disanfang_kaifa_jiaocheng_shijian_xiangmu_mianshiti_fix1-2025.3.25.0.dist-info/WHEEL
how2j_disanfang_kaifa_jiaocheng_shijian_xiangmu_mianshiti_fix1-2025.3.25.0.dist-info/entry_points.txt
how2j_disanfang_kaifa_jiaocheng_shijian_xiangmu_mianshiti_fix1-2025.3.25.0.dist-info/top_level.txt
how2j_disanfang_kaifa_jiaocheng_shijian_xiangmu_mianshiti_fix1-2025.3.25.0.dist-info/RECORD
